protocolws/__init__.py
protocolws/protocol.py
protocolws-0.2.dist-info/METADATA
protocolws-0.2.dist-info/RECORD
protocolws-0.2.dist-info/WHEEL
protocolws-0.2.dist-info/top_level.txt
